duolibre/__init__.py
duolibre/duolibre.py
duolibre-1.0.1.dist-info/LICENSE
duolibre-1.0.1.dist-info/METADATA
duolibre-1.0.1.dist-info/WHEEL
duolibre-1.0.1.dist-info/entry_points.txt
duolibre-1.0.1.dist-info/top_level.txt
duolibre-1.0.1.dist-info/RECORD
