Metadata-Version: 2.1
Name: duolibre
Version: 1.0.1
Summary: Authenticate to Duo 2FA systems without the proprietary Duo Mobile app
Home-page: https://github.com/evan-goode/duolibre
Author: Evan Goode
Author-email: mail@evangoo.de
License: The Unlicense
Platform: UNKNOWN
Requires-Dist: Click
Requires-Dist: pycryptodome
Requires-Dist: pyotp
Requires-Dist: qrcode
Requires-Dist: requests
